[{"key":"SCENARIO_s20_39000100_04_0000","text":"Motion"},
{"key":"SCENARIO_s20_39000100_04_0010","text":"あ！\n甜花ちゃーん！　ぼろぼろこぼしちゃってるよ～！"},
{"key":"SCENARIO_s20_39000100_04_0020","text":"……へ……？"},
{"key":"SCENARIO_s20_39000100_04_0030","text":"ドーナツお洋服に落ちてるから\n動かないでね……！　そのまま……！"},
{"key":"SCENARIO_s20_39000100_04_0040","text":"ちょっと待って\n何か拭くもの……"},
{"key":"SCENARIO_s20_39000100_04_0050","text":"はい、どうぞ～"},
{"key":"SCENARIO_s20_39000100_04_0060","text":"ありがとう……！\nこれで拭いて……ゴミ箱に払いましょう"},
{"key":"SCENARIO_s20_39000100_04_0070","text":"んー……\n──っ……！？"},
{"key":"SCENARIO_s20_39000100_04_0080","text":"甜花ちゃん！？\n……はいっ！　飲み物っ！"},
{"key":"SCENARIO_s20_39000100_04_0090","text":"──……あ、あぅ……\n…………にへへ、このドーナツ、美味しい……"},
{"key":"SCENARIO_s20_39000100_04_0100","text":"ふふっ\nそれならよかったです～"}]