[{"key":"SCENARIO_s10_10900100_03_0001","text":"Motion"},
{"key":"SCENARIO_s10_10900100_03_0062","text":"Motion"},
{"key":"SCENARIO_s10_10900100_03_0031","text":"Motion"},
{"key":"SCENARIO_s10_10900100_03_0061","text":"Motion"},
{"key":"SCENARIO_s10_10900100_03_0010","text":"…………！"},
{"key":"SCENARIO_s10_10900100_03_0020","text":"(Looks like she\u0027s excited...)"},
{"key":"SCENARIO_s10_10900100_03_0030","text":"I\u0027m coming out now!"},
{"key":"SCENARIO_s10_10900100_03_0040","text":"P-Producer-san,\nIs that by any chance...!"},
{"key":"SCENARIO_s10_10900100_03_0050","text":"Yeah, it\u0027s the costume you\u0027ve been waiting for, Kaho.\nWant to try it on?"},
{"key":"SCENARIO_s10_10900100_03_0060","text":"Yes!"},
{"key":"SCENARIO_s10_10900100_03_0070","text":"Producer-san! I\u0027ve put it on!"},
{"key":"SCENARIO_s10_10900100_03_0080","text":"Wow...\nYeah, it looks great on you. Really suits you."},
{"key":"SCENARIO_s10_10900100_03_0090","text":"Hehe,\nWith this──I\u0027ll make my dreams come true!"},
{"key":"SCENARIO_s10_10900100_03_0100","text":"That\u0027s right, I\u0027ll do my best too,\nLet\u0027s make them come true together."}]
