[{"key":"SCENARIO_s10_12100200_01_0000","text":"Motion"},
{"key":"SCENARIO_s10_12100200_01_0010","text":"……ああ、遅くなっちゃったな\nみんないないだろうし、郵便物だけチェックして──"},
{"key":"SCENARIO_s10_12100200_01_0020","text":"お疲れ様です"},
{"key":"SCENARIO_s10_12100200_01_0030","text":"あれ、お疲れ様！\n帰るところか？"},
{"key":"SCENARIO_s10_12100200_01_0040","text":"はい"},
{"key":"SCENARIO_s10_12100200_01_0050","text":"ちょうどよかった\n……これ、持って帰ってくれ"},
{"key":"SCENARIO_s10_12100200_01_0060","text":"なんですか？"},
{"key":"SCENARIO_s10_12100200_01_0070","text":"今日発売の雑誌だよ\n巻頭で２８３のみんなを特集してもらっている"},
{"key":"SCENARIO_s10_12100200_01_0080","text":"荷物になるけどよければ１冊──"},
{"key":"SCENARIO_s10_12100200_01_0090","text":"結構です、他の人に差し上げてください\n……お先に失礼します"},
{"key":"SCENARIO_s10_12100200_01_0100","text":"えっ、ああいや\n全員分ちゃんとあって……おーい……！"}]