[{"key":"SCENARIO_s09_01012100_02_0000","text":"Motion"},
{"key":"SCENARIO_s09_01012100_02_0011","text":"Motion"},
{"key":"SCENARIO_s09_01012100_02_0031","text":"Motion"},
{"key":"SCENARIO_s09_01012100_02_0051","text":"Motion"},
{"key":"SCENARIO_s09_01012100_02_0161","text":"Motion"},
{"key":"SCENARIO_s09_01012100_02_0010","text":"────────Ugh, whoa...!"},
{"key":"SCENARIO_s09_01012100_02_0020","text":"............?"},
{"key":"SCENARIO_s09_01012100_02_0030","text":"Ha, ha... haa...!\n────────Phew..."},
{"key":"SCENARIO_s09_01012100_02_0040","text":"...Is it post-meal running?"},
{"key":"SCENARIO_s09_01012100_02_0050","text":"Huh? Uh, yeah...\nInitially, it was just a stroll, though... but ended up..."},
{"key":"SCENARIO_s09_01012100_02_0060","text":"...Madoka, are you also taking a walk?"},
{"key":"SCENARIO_s09_01012100_02_0070","text":"...It\u0027s none of your concern, right?"},
{"key":"SCENARIO_s09_01012100_02_0080","text":"Well, yeah,\nthat\u0027s true, but..."},
{"key":"SCENARIO_s09_01012100_02_0090","text":"Oh, hey! There are fruits in the cafeteria fridge.\nWant to have some together?"},
{"key":"SCENARIO_s09_01012100_02_0100","text":"...It\u0027s free time, so..."},
{"key":"SCENARIO_s09_01012100_02_0110","text":"Yeah, true...\nBut... it\u0027s already night, and it\u0027s dark outside..."},
{"key":"SCENARIO_s09_01012100_02_0120","text":"...You\u0027re being overly protective.\nThere are streetlights within the premises."},
{"key":"SCENARIO_s09_01012100_02_0130","text":"Yeah... well... but, you know, I want you to think about it.\nThis place is rich in nature, right...?"},
{"key":"SCENARIO_s09_01012100_02_0140","text":"In such places... it\u0027s not just humans\nwho are attracted to light, you know...?"},
{"key":"SCENARIO_s09_01012100_02_0150","text":"Um... I think it\u0027s better not to be too explicit\nwith Madoka, but, in short... moths..."},
{"key":"SCENARIO_s09_01012100_02_0160","text":"──────Fruits."},
{"key":"SCENARIO_s09_01012100_02_0170","text":"I\u0027ll take some.\n............In the cafeteria, right?"},
{"key":"SCENARIO_s09_01012100_02_0180","text":"Oh, uh, yeah...!\nAlright, let\u0027s eat...!"}]
