[{"key":"SCENARIO_s42_01050100_00_0003","text":"Motion"},
{"key":"SCENARIO_s42_01050100_00_0021","text":"Motion"},
{"key":"SCENARIO_s42_01050100_00_0031","text":"Motion"},
{"key":"SCENARIO_s42_01050100_00_0161","text":"Motion"},
{"key":"SCENARIO_s42_01050100_00_0171","text":"Motion"},
{"key":"SCENARIO_s42_01050100_00_0000","text":"Magazine Articles"},
{"key":"SCENARIO_s42_01050100_00_0001","text":"Magazine Articles"},
{"key":"SCENARIO_s42_01050100_00_0002","text":"Interviewer"},
{"key":"SCENARIO_s42_01050100_00_0010","text":"\u0022The Straylight live event,\nwhich ended amidst loud cheers.\u0022"},
{"key":"SCENARIO_s42_01050100_00_0020","text":"\u0022Thinking about the next stage,\nexpectations inevitably rise──\u0022"},
{"key":"SCENARIO_s42_01050100_00_0030","text":"Oh～! Fuyuko-chan, look～\nwe’re being praised so much～♪"},
{"key":"SCENARIO_s42_01050100_00_0040","text":"I see......that’s good."},
{"key":"SCENARIO_s42_01050100_00_0050","text":"Huh......?\nFuyuko-chan, you don’t seem too happy?"},
{"key":"SCENARIO_s42_01050100_00_0060","text":"It’s not that I’m not happy......"},
{"key":"SCENARIO_s42_01050100_00_0070","text":"As a fan, I will continue to follow all of you!\nThe best unit, Straylight’s success!"},
{"key":"SCENARIO_s42_01050100_00_0080","text":"If it’s that interviewer, I only think that of course\nit’s going to be an article full of praise."},
{"key":"SCENARIO_s42_01050100_00_0090","text":"I see～, I’m like yay～ We were praised twice,\nin the interview and in the article!"},
{"key":"SCENARIO_s42_01050100_00_0100","text":"......"},
{"key":"SCENARIO_s42_01050100_00_0110","text":"Hey, what do you think, Producer～?"},
{"key":"SCENARIO_s42_01050100_00_0120","text":"......Well, I’m honestly happy that everyone is being praised.\nI can’t deny a bit of favoritism though......"},
{"key":"SCENARIO_s42_01050100_00_0130","text":"But, the reason the interviewer became a fan\nis because of everyone’s hard work."},
{"key":"SCENARIO_s42_01050100_00_0140","text":"......"},
{"key":"SCENARIO_s42_01050100_00_0150","text":"Well, that might be true."},
{"key":"SCENARIO_s42_01050100_00_0160","text":"Ahaha～♪\nWe’ll have to work hard again～!"},
{"key":"SCENARIO_s42_01050100_00_0170","text":"Aah......\nWe’re out of snacks......"},
{"key":"SCENARIO_s42_01050100_00_0180","text":"Oh, by the way, talking about this\njust reminded me of something."},
{"key":"SCENARIO_s42_01050100_00_0190","text":"? Ah, what is it?"},
{"key":"SCENARIO_s42_01050100_00_0200","text":"The interviewer\nsaid something──"}]
