[{"key":"SCENARIO_s43_01010000_01_0000","text":"Motion"},
{"key":"SCENARIO_s43_01010000_01_0010","text":"...Ah, you\u0027re here"},
{"key":"SCENARIO_s43_01010000_01_0020","text":"This is about our future promotional material\n...I\u0027m sure you have a rough idea of it."},
{"key":"SCENARIO_s43_01010000_01_0030","text":"This will be an approach that could give more\nopportunities to 283PRO idols."},
{"key":"SCENARIO_s43_01010000_01_0040","text":"I\u0027d like to hear your opinion.\n...What do you think?\u0022"},
{"key":"SCENARIO_s43_01010000_01_0041","text":"Motion"},
{"key":"SCENARIO_s43_01010000_01_0050","text":"Yeah, I agree..."},
{"key":"SCENARIO_s43_01010000_01_0060","text":"After all, it would be real-time streaming. We can create\nmore chances than ever for our idols to communicate..."},
{"key":"SCENARIO_s43_01010000_01_0070","text":"I believe that this will bring the voices\nof idols closer to as many people as possible."},
{"key":"SCENARIO_s43_01010000_01_0080","text":"...It\u0027s okay"},
{"key":"SCENARIO_s43_01010000_01_0090","text":"Do what you think is right,\nHazuki, please support him."},
{"key":"SCENARIO_s43_01010000_01_0100","text":" I\u0027ll leave it to you both."},
{"key":"SCENARIO_s43_01010000_01_0110","text":"Yes! / Yes~"}]
