[{"key":"SCENARIO_s10_20400300_02_0000","text":"Motion"},
{"key":"SCENARIO_s10_20400300_02_0001","text":"Motion"},
{"key":"SCENARIO_s10_20400300_02_0002","text":"Motion"},
{"key":"SCENARIO_s10_20400300_02_0101","text":"Motion"},
{"key":"SCENARIO_s10_20400300_02_0010","text":"Producer, listen to this, listen to this~!\nI did some research..."},
{"key":"SCENARIO_s10_20400300_02_0020","text":"Huh? What about?"},
{"key":"SCENARIO_s10_20400300_02_0030","text":"You mentioned it the other day, didn\u0027t you?\nAbout the real Venice Carnival!"},
{"key":"SCENARIO_s10_20400300_02_0040","text":"During the carnival, there\u0027s an event where people wear masks,\ndress up as angels, and descend from the top of the bell tower."},
{"key":"SCENARIO_s10_20400300_02_0050","text":"So, Producer,\nI thought it would be cool to try that too~!"},
{"key":"SCENARIO_s10_20400300_02_0060","text":"Haha, I see.\nThat would be pretty cool, huh?"},
{"key":"SCENARIO_s10_20400300_02_0070","text":"Yeah, right? Yeah, right?\nThere are other cool things too~"},
{"key":"SCENARIO_s10_20400300_02_0080","text":"Oh, what\u0027s that?"},
{"key":"SCENARIO_s10_20400300_02_0090","text":"A parade of people wearing masks~!"},
{"key":"SCENARIO_s10_20400300_02_0100","text":"Oh, I see, there\u0027s something like that.\nCan you show me that information too?"}]
