[{"key":"SCENARIO_s03_07030000_00_0011","text":"Motion"},
{"key":"SCENARIO_s03_07030000_00_0010","text":"にちか\nドーナツ買ってきたけど食べるか？"},
{"key":"SCENARIO_s03_07030000_00_0020","text":"……冗談で言ってます？\nいちばん太るやつじゃないですかー"},
{"key":"SCENARIO_s03_07030000_00_0030","text":"あれ、いらないのか？"},
{"key":"SCENARIO_s03_07030000_00_0040","text":"…………食べますけど"},
{"key":"SCENARIO_s03_07030000_00_0005","text":"和菓子とかなら\nよかったか……"},
{"key":"SCENARIO_s03_07030000_00_0006","text":"無理しなくて\nいいんだ"},
{"key":"SCENARIO_s03_07030000_00_0007","text":"食べたぶん動けば\nいいんじゃないか？"},
{"key":"SCENARIO_s03_07030000_01_0011","text":"Motion"},
{"key":"SCENARIO_s03_07030000_01_0010","text":"べつに、カロリーとかの問題じゃないですけど……"},
{"key":"SCENARIO_s03_07030000_01_0020","text":"じゃリンク送るので\n次は和菓子のいいやつお願いしますー"},
{"key":"SCENARIO_s03_07030000_02_0011","text":"Motion"},
{"key":"SCENARIO_s03_07030000_02_0010","text":"……っ"},
{"key":"SCENARIO_s03_07030000_02_0020","text":"食べますって言ってますー……！"},
{"key":"SCENARIO_s03_07030000_03_0011","text":"Motion"},
{"key":"SCENARIO_s03_07030000_03_0010","text":"……っ"},
{"key":"SCENARIO_s03_07030000_03_0020","text":"食べさせたいのか運動させたいのか\nどっちなんです……！？"}]
