[{"key":"SCENARIO_s20_10800100_01_0000","text":"Motion"},
{"key":"SCENARIO_s20_10800100_01_0010","text":"──────あ……"},
{"key":"SCENARIO_s20_10800100_01_0020","text":"恋鐘ちゃんの……前髪に……\n────待ってね……"},
{"key":"SCENARIO_s20_10800100_01_0030","text":"ふぇ……\nなんか付いとると～？"},
{"key":"SCENARIO_s20_10800100_01_0040","text":"うん……\nこれ────"},
{"key":"SCENARIO_s20_10800100_01_0050","text":"────雪～？"},
{"key":"SCENARIO_s20_10800100_01_0060","text":"ふふっ……\n雪じゃ……なさそう……"},
{"key":"SCENARIO_s20_10800100_01_0070","text":"綿毛……"},
{"key":"SCENARIO_s20_10800100_01_0071","text":"Motion"},
{"key":"SCENARIO_s20_10800100_01_0080","text":"──────あ～っ……！"},
{"key":"SCENARIO_s20_10800100_01_0090","text":"……\n帰って……いっちゃった……"},
{"key":"SCENARIO_s20_10800100_01_0100","text":"またね──────"}]