[{"key":"SCENARIO_s10_22200100_03_0000","text":"Motion"},
{"key":"SCENARIO_s10_22200100_03_0010","text":"Ehehe..."},
{"key":"SCENARIO_s10_22200100_03_0020","text":"Haha, I\u0027m glad Koito likes it."},
{"key":"SCENARIO_s10_22200100_03_0030","text":"It turned out to be a good outfit, right?"},
{"key":"SCENARIO_s10_22200100_03_0040","text":"Yes...!\nIt\u0027s really...!"},
{"key":"SCENARIO_s10_22200100_03_0050","text":"And, the design is cute, but\nIt\u0027s not just that..."},
{"key":"SCENARIO_s10_22200100_03_0060","text":"Y-Yes,\nBecause it\u0027s... our..."},
{"key":"SCENARIO_s10_22200100_03_0070","text":"Because it\u0027s our own outfit...!"},
{"key":"SCENARIO_s10_22200100_03_0080","text":"...Yeah."},
{"key":"SCENARIO_s10_22200100_03_0090","text":"Let\u0027s wear it and put on a great performance,\nThe four of us from noctchill."},
{"key":"SCENARIO_s10_22200100_03_0100","text":"...!\nYes...!"}]
