[{"key":"SCENARIO_s10_22000200_02_0000","text":"Motion"},
{"key":"SCENARIO_s10_22000200_02_0010","text":"………………"},
{"key":"SCENARIO_s10_22000200_02_0020","text":"…………あー"},
{"key":"SCENARIO_s10_22000200_02_0030","text":"……ん？　\nどうした、透"},
{"key":"SCENARIO_s10_22000200_02_0040","text":"なんか、降るかも\n雨"},
{"key":"SCENARIO_s10_22000200_02_0050","text":"え……"},
{"key":"SCENARIO_s10_22000200_02_0060","text":"………………\nあ、きた。ぽつって"},
{"key":"SCENARIO_s10_22000200_02_0070","text":"うわ、まずいな……"},
{"key":"SCENARIO_s10_22000200_02_0080","text":"まずい？"},
{"key":"SCENARIO_s10_22000200_02_0090","text":"今日、傘、持ってきてなくてさ……\n……少し急ぐか"},
{"key":"SCENARIO_s10_22000200_02_0100","text":"うん"}]