[{"key":"SCENARIO_s41_15000000_01_0000","text":"Motion"},
{"key":"SCENARIO_s41_15000000_01_0010","text":"──A-Auu............"},
{"key":"SCENARIO_s41_15000000_01_0020","text":"Tenka......\nreally is...... a failure......"},
{"key":"SCENARIO_s41_15000000_01_0030","text":"............"},
{"key":"SCENARIO_s41_15000000_01_0040","text":"That\u0027s not true...!\nYou were really working hard at today\u0027s recording."},
{"key":"SCENARIO_s41_15000000_01_0050","text":"B-But......\nTenka...... screwed up... her role in the drama......"},
{"key":"SCENARIO_s41_15000000_01_0060","text":"Even though... she was just an extra......"},
{"key":"SCENARIO_s41_15000000_01_0070","text":"She sat... in the wrong spot......\nThey had to keep stopping... the shoot......"},
{"key":"SCENARIO_s41_15000000_01_0080","text":"Tenka... caused so many issues...\nfor everyone else......"},
{"key":"SCENARIO_s41_15000000_01_0081","text":"Motion"},
{"key":"SCENARIO_s41_15000000_01_0090","text":"......Tenka──"},
{"key":"SCENARIO_s41_15000000_01_0100","text":"Really isn\u0027t......\ncut out to be an idol......"},
{"key":"SCENARIO_s41_15000000_01_0110","text":"...Tenka..."},
{"key":"SCENARIO_s41_15000000_01_0120","text":"It was just one small mistake.\nPlease don\u0027t say you\u0027re not cut out for it."},
{"key":"SCENARIO_s41_15000000_01_0130","text":"This is the first time you\u0027ve done work in a drama.\nOf course you\u0027re going to screw up sometimes."},
{"key":"SCENARIO_s41_15000000_01_0140","text":"Besides, you\u0027re────"},
{"key":"SCENARIO_s41_15000000_01_0150","text":"──Oh, i\u0027m getting a call......"},
{"key":"SCENARIO_s41_15000000_01_0160","text":"Sorry Tenka,\njust give me a second."},
{"key":"SCENARIO_s41_15000000_01_0170","text":"S-Sure......"},
{"key":"SCENARIO_s41_15000000_01_0171","text":"Motion"},
{"key":"SCENARIO_s41_15000000_01_0180","text":"──Tenka!\nGood news...! Congratulations!!"},
{"key":"SCENARIO_s41_15000000_01_0190","text":"......Huh......\nW-What\u0027s up......?"},
{"key":"SCENARIO_s41_15000000_01_0200","text":"Oh, sorry...!\nGot a little excited there......"},
{"key":"SCENARIO_s41_15000000_01_0210","text":"So, the people at that drama from today...\nThey said they want you as an extra again!"},
{"key":"SCENARIO_s41_15000000_01_0220","text":"Wha......!"},
{"key":"SCENARIO_s41_15000000_01_0230","text":"I-Is it actually okay......?\nSince, you know... Tenka... screwed up......"},
{"key":"SCENARIO_s41_15000000_01_0240","text":"Yeah!"},
{"key":"SCENARIO_s41_15000000_01_0250","text":"They said, \u0022Sure, she screwed up, but seeing her\nworking so hard sure left an impression on us.\u0022"},
{"key":"SCENARIO_s41_15000000_01_0260","text":"R-Really......?"},
{"key":"SCENARIO_s41_15000000_01_0270","text":"──I think that\u0027s one of your appeals too, Tenka."},
{"key":"SCENARIO_s41_15000000_01_0280","text":"......?"},
{"key":"SCENARIO_s41_15000000_01_0290","text":"You\u0027re always working so hard, from the bottom of\nyour heart, yeah?"},
{"key":"SCENARIO_s41_15000000_01_0300","text":"Like, even if you happen to screw up──\nYou never give up, and give it your all."},
{"key":"SCENARIO_s41_15000000_01_0310","text":"I think that everyone is inspired by that part of you,\nTenka."},
{"key":"SCENARIO_s41_15000000_01_0320","text":"............"},
{"key":"SCENARIO_s41_15000000_01_0330","text":"──Also"},
{"key":"SCENARIO_s41_15000000_01_0340","text":"There\u0027s still a lot you can\u0027t do right now,\nand you may very well screw up at times,"},
{"key":"SCENARIO_s41_15000000_01_0350","text":"But you\u0027re making sure to grow at your own pace."},
{"key":"SCENARIO_s41_15000000_01_0360","text":"That\u0027s how I feel, as someone who\u0027s been keeping an\neye on you while you\u0027ve been here."},
{"key":"SCENARIO_s41_15000000_01_0370","text":"......So, I want you to have a bit more self-confidence.\nYou\u0027ll be able to do it even better next time."},
{"key":"SCENARIO_s41_15000000_01_0380","text":"............\n...Y-You think so.......?"},
{"key":"SCENARIO_s41_15000000_01_0390","text":"Well...\nif you\u0027re going to say all of that......"},
{"key":"SCENARIO_s41_15000000_01_0400","text":"Tenka\u0027s gonna... try working even harder... at the\nnext one......!"}]
