[{"key":"SCENARIO_s20_11900100_02_0000","text":"Motion"},
{"key":"SCENARIO_s20_11900100_02_0010","text":"...Since you said you wanted to think about the order,\nI agreed to help, but... do you have any ideas, Mei?"},
{"key":"SCENARIO_s20_11900100_02_0020","text":"Hmm..."},
{"key":"SCENARIO_s20_11900100_02_0030","text":"...\n...Asahi-chan, Fuyuko-chan!"},
{"key":"SCENARIO_s20_11900100_02_0040","text":"I\u0027ll think about the rest!"},
{"key":"SCENARIO_s20_11900100_02_0050","text":"Eh, but\naren\u0027t you going to do it alone──"},
{"key":"SCENARIO_s20_11900100_02_0060","text":"I don\u0027t want to burden them any further\nand I was the one who brought it up."},
{"key":"SCENARIO_s20_11900100_02_0070","text":"Besides, they have meetings tomorrow, right!?\nSo, it\u0027s just right for me to do it!"},
{"key":"SCENARIO_s20_11900100_02_0080","text":"...If you\u0027re being considerate,\nI wish you\u0027d done it before getting them involved."},
{"key":"SCENARIO_s20_11900100_02_0090","text":"...Well, keep at it until you\u0027re satisfied."},
{"key":"SCENARIO_s20_11900100_02_0100","text":"Ahaha, alright!"}]
