[{"key":"SCENARIO_s42_01060100_00_0000","text":"Motion"},
{"key":"SCENARIO_s42_01060100_00_0010","text":"Hey, Koito-chan"},
{"key":"SCENARIO_s42_01060100_00_0020","text":"Look~"},
{"key":"SCENARIO_s42_01060100_00_0030","text":"Wow, that tart looks delicious...!"},
{"key":"SCENARIO_s42_01060100_00_0040","text":"Hey~"},
{"key":"SCENARIO_s42_01060100_00_0050","text":"But...\nit says it\u0027s for a limited time only..."},
{"key":"SCENARIO_s42_01060100_00_0060","text":"Ah~\nIsn\u0027t it okay as long as we go during the limited period?"},
{"key":"SCENARIO_s42_01060100_00_0070","text":"Koito-chan, when do you think we can go?"},
{"key":"SCENARIO_s42_01060100_00_0080","text":"Eh...!\nCan I go too?"},
{"key":"SCENARIO_s42_01060100_00_0090","text":"Huh~?\nKoito-chan, don\u0027t you want to eat it?"},
{"key":"SCENARIO_s42_01060100_00_0100","text":"...B-but, um...\nI wonder if I can go..."},
{"key":"SCENARIO_s42_01060100_00_0101","text":"Motion"},
{"key":"SCENARIO_s42_01060100_00_0110","text":"...Um,\nC-can I go...?"},
{"key":"SCENARIO_s42_01060100_00_0120","text":"……？"},
{"key":"SCENARIO_s42_01060100_00_0130","text":"I\u0027m... um,\npretty busy this week...!"},
{"key":"SCENARIO_s42_01060100_00_0140","text":"Ah~"},
{"key":"SCENARIO_s42_01060100_00_0150","text":"Then, when Koito-chan can go,\nlet\u0027s go eat together~?"},
{"key":"SCENARIO_s42_01060100_00_0153","text":"Motion"},
{"key":"SCENARIO_s42_01060100_00_0151","text":"Motion"},
{"key":"SCENARIO_s42_01060100_00_0152","text":"Motion"},
{"key":"SCENARIO_s42_01060100_00_0160","text":"...Huh?\nHinana, you\u0027re here."},
{"key":"SCENARIO_s42_01060100_00_0170","text":"Yeah~\nI came for a snack~"},
{"key":"SCENARIO_s42_01060100_00_0180","text":"I see ...Since she\u0027s here,\nmaybe I should talk to Hinana about our next job."},
{"key":"SCENARIO_s42_01060100_00_0190","text":"……？"},
{"key":"SCENARIO_s42_01060100_00_0200","text":"It\u0027s about the upcoming job─"}]
