[{"key":"SCENARIO_s10_12100300_03_0000","text":"Motion"},
{"key":"SCENARIO_s10_22100700_03_0091","text":"Motion"},
{"key":"SCENARIO_s10_22100700_03_0010","text":"────Madoka!\nGreat job with the shoot."},
{"key":"SCENARIO_s10_22100700_03_0020","text":"Good job.\n...If there\u0027s anything you noticed."},
{"key":"SCENARIO_s10_22100700_03_0030","text":"Ah, no, there were no problems at all.\nIt was really good."},
{"key":"SCENARIO_s10_22100700_03_0040","text":"But if I had to point out something... let\u0027s see...\nYour smile might have been the most memorable part."},
{"key":"SCENARIO_s10_22100700_03_0050","text":"...In a good way? Or a bad way?"},
{"key":"SCENARIO_s10_22100700_03_0060","text":"Huh?\nOh, of course in a good way!"},
{"key":"SCENARIO_s10_22100700_03_0070","text":"...I see, that\u0027s a relief.\nIf that\u0027s enough to get a good evaluation."},
{"key":"SCENARIO_s10_22100700_03_0080","text":"...Of course, if you have an even better smile,\nI\u0027d love to see it someday."},
{"key":"SCENARIO_s10_22100700_03_0090","text":"...Understood."},
{"key":"SCENARIO_s10_22100700_03_0100","text":"I won\u0027t show you.\nDefinitely not to you."}]
