[{"key":"SCENARIO_s09_01011900_03_0000","text":"Motion"},
{"key":"SCENARIO_s09_01011900_03_0010","text":"……"},
{"key":"SCENARIO_s09_01011900_03_0020","text":"──……どう？"},
{"key":"SCENARIO_s09_01011900_03_0030","text":"うん！　さすがだな\nものすごく上達してる"},
{"key":"SCENARIO_s09_01011900_03_0040","text":"マジで！？\nよっしゃー！"},
{"key":"SCENARIO_s09_01011900_03_0050","text":"休み時間もずっと練習していたもんな\n頑張った成果が出ていると思う"},
{"key":"SCENARIO_s09_01011900_03_0060","text":"ま～……、確かに\nそういうカンジ、あったり～？"},
{"key":"SCENARIO_s09_01011900_03_0070","text":"けど、トレーナーさんには\nまだやれるって言われてるから"},
{"key":"SCENARIO_s09_01011900_03_0080","text":"完璧にするぞ～！\n的な気分～！"},
{"key":"SCENARIO_s09_01011900_03_0090","text":"はは、そうだな\n愛依ならできるよ、絶対に"},
{"key":"SCENARIO_s09_01011900_03_0100","text":"──まだもうちょっと練習するんだろう？\n飲み物を買ってこようと思うけど、欲しいものとか──"},
{"key":"SCENARIO_s09_01011900_03_0110","text":"！　それなら大丈夫だし！"},
{"key":"SCENARIO_s09_01011900_03_0120","text":"合宿所のおばちゃんがさ『助けてくれたお礼に』って\nジュースくれた系だから！"},
{"key":"SCENARIO_s09_01011900_03_0130","text":"え……！？\nくれたって、こんなにたくさん……！？"},
{"key":"SCENARIO_s09_01011900_03_0140","text":"はは……そっか……\n愛依の優しさが本当に嬉しかったんだな…………"},
{"key":"SCENARIO_s09_01011900_03_0150","text":"マジでテンション上がっちゃったわ～\nあ、プロデューサーも何本かもらって……！"},
{"key":"SCENARIO_s09_01011900_03_0160","text":"……じゃあ、一本だけ\nせっかく愛依がもらったものだからさ"},
{"key":"SCENARIO_s09_01011900_03_0170","text":"えー、プロデューサーも一緒に掃除してくれたし！\n一緒に飲もうよ、ね……！"},
{"key":"SCENARIO_s09_01011900_03_0171","text":"Motion"},
{"key":"SCENARIO_s09_01011900_03_0180","text":"────……\nっしゃ！　気合も入れたし、続きやるぞ～"},
{"key":"SCENARIO_s09_01011900_03_0190","text":"プロデューサーと一緒なら、\nうちはちょー最強！　だからね！"}]