[{"key":"SCENARIO_s09_01012200_03_0000","text":"Motion"},
{"key":"SCENARIO_s09_01012200_03_0071","text":"Motion"},
{"key":"SCENARIO_s09_01012200_03_0161","text":"Motion"},
{"key":"SCENARIO_s09_01012200_03_0010","text":"Um...\nFor today\u0027s lesson──"},
{"key":"SCENARIO_s09_01012200_03_0020","text":"Koito.\nYou\u0027ve been taking notes properly till the end."},
{"key":"SCENARIO_s09_01012200_03_0030","text":"......!\nP-Producer-san...!"},
{"key":"SCENARIO_s09_01012200_03_0040","text":"Haha, finished writing?\nEven for today\u0027s portion?"},
{"key":"SCENARIO_s09_01012200_03_0050","text":"Y-Yes...!"},
{"key":"SCENARIO_s09_01012200_03_0060","text":"Alright, then show me.\nSummarize everything you\u0027ve written so far."},
{"key":"SCENARIO_s09_01012200_03_0070","text":"Ah... Yes.\nP-Please take a look...!"},
{"key":"SCENARIO_s09_01012200_03_0080","text":"You\u0027ve been writing diligently every day.\nWith this much, it means Koito has achieved results."},
{"key":"SCENARIO_s09_01012200_03_0090","text":"I-Is that so...?"},
{"key":"SCENARIO_s09_01012200_03_0100","text":".........\nIt would be nice if that were the case..."},
{"key":"SCENARIO_s09_01012200_03_0110","text":"I\u0027ve told you, haven\u0027t I? If there\u0027s something\nnew you can do or something you\u0027ve learned,"},
{"key":"SCENARIO_s09_01012200_03_0120","text":"That\u0027s something to be happy about.\nI\u0027m also very happy."},
{"key":"SCENARIO_s09_01012200_03_0130","text":"...Producer-san too?"},
{"key":"SCENARIO_s09_01012200_03_0140","text":"Yeah, of course!\nFor this much, if Koito gains something,"},
{"key":"SCENARIO_s09_01012200_03_0150","text":"I truly believe it was worth it\nto come to the training camp."},
{"key":"SCENARIO_s09_01012200_03_0160","text":"...Producer-san..."},
{"key":"SCENARIO_s09_01012200_03_0170","text":"T-That\u0027s right...\nI\u0027m also glad I came to the training camp...!"},
{"key":"SCENARIO_s09_01012200_03_0180","text":"T-Thank you... and\nplease continue to take care of me, Producer-san."}]
