[{"key":"SCENARIO_s10_31100200_01_0000","text":"Motion"},
{"key":"SCENARIO_s10_31100200_01_0101","text":"Motion"},
{"key":"SCENARIO_s10_31100200_01_0010","text":"This outfit,\nlooks like a marching band uniform, doesn\u0027t it?"},
{"key":"SCENARIO_s10_31100200_01_0020","text":"Yeah, it does."},
{"key":"SCENARIO_s10_31100200_01_0030","text":"...I wonder if we\u0027ll march around\nlike a marching band?"},
{"key":"SCENARIO_s10_31100200_01_0040","text":"Come to think of it, I\u0027ve seen pictures like that before.\nPlaying music in the forest while leading animals..."},
{"key":"SCENARIO_s10_31100200_01_0050","text":"--What kind of animal would you like to march with, Juri?"},
{"key":"SCENARIO_s10_31100200_01_0060","text":"Ahaha, let me think...\nHmm... Maybe cats...?"},
{"key":"SCENARIO_s10_31100200_01_0070","text":"But cats seem so independent,\nthey might not follow."},
{"key":"SCENARIO_s10_31100200_01_0080","text":"I wonder?\nIf you become friends, they might follow."},
{"key":"SCENARIO_s10_31100200_01_0090","text":"Become friends... Can we really?"},
{"key":"SCENARIO_s10_31100200_01_0100","text":"Haha, Juri is kind, so if that comes across,\nthey\u0027ll probably follow."}]
