[{"key":"SCENARIO_s20_32600100_03_0000","text":"Motion"},
{"key":"SCENARIO_s20_32600100_03_0101","text":"Motion"},
{"key":"SCENARIO_s20_32600100_03_0010","text":"... Hmm..."},
{"key":"SCENARIO_s20_32600100_03_0020","text":"I just can\u0027t seem to decide."},
{"key":"SCENARIO_s20_32600100_03_0030","text":"It feels like I\u0027m just standing there,\ninstead of striking a pose."},
{"key":"SCENARIO_s20_32600100_03_0040","text":"Do you think so...? I feel like it\u0027s already perfect,\nbut what could be missing...?"},
{"key":"SCENARIO_s20_32600100_03_0050","text":"Hey, what do you think, Luca-chan?"},
{"key":"SCENARIO_s20_32600100_03_0060","text":"... Just take a picture and see how it looks.\nUse your smartphone..."},
{"key":"SCENARIO_s20_32600100_03_0070","text":"Huh?"},
{"key":"SCENARIO_s20_32600100_03_0080","text":"But there\u0027s a difference between\nlooking in the mirror and taking a photo..."},
{"key":"SCENARIO_s20_32600100_03_0090","text":"Oh, I see...!"},
{"key":"SCENARIO_s20_32600100_03_0100","text":"Yeah, yeah...! Then I\u0027ll take the picture~\nThank you, Luca-chan!"}]
