[{"key":"SCENARIO_s20_30500200_03_0000","text":"Motion"},
{"key":"SCENARIO_s20_30500200_03_0001","text":"Motion"},
{"key":"SCENARIO_s20_30500200_03_0010","text":"What\u0027s wrong, Kiriko?"},
{"key":"SCENARIO_s20_30500200_03_0020","text":"The sound of the waves...\nThey\u0027re going \u0022zazaaa... zazaan\u0022"},
{"key":"SCENARIO_s20_30500200_03_0030","text":"Like it\u0027s slowly...\nSoaking into me..."},
{"key":"SCENARIO_s20_30500200_03_0040","text":"Soaking into you?"},
{"key":"SCENARIO_s20_30500200_03_0050","text":"Yeah...\nand also... the smell of the sea..."},
{"key":"SCENARIO_s20_30500200_03_0051","text":"Motion"},
{"key":"SCENARIO_s20_30500200_03_0060","text":"Ahh... Now that you mention it, I\u0027ve heard that\nsounds and smells are a big influence on memories."},
{"key":"SCENARIO_s20_30500200_03_0070","text":"Ah indeed. It\u0027s pretty common for them to trigger\nvarious recollections."},
{"key":"SCENARIO_s20_30500200_03_0080","text":"Nfufu～\nIt\u0027s makin\u0027 me remember my hometown～"},
{"key":"SCENARIO_s20_30500200_03_0081","text":"Motion"},
{"key":"SCENARIO_s20_30500200_03_0090","text":"Fufu..."},
{"key":"SCENARIO_s20_30500200_03_0100","text":"And certainly... this memory, too..."}]
