[{"key":"SCENARIO_s01_08010000_05_0000","text":"Motion"},
{"key":"SCENARIO_s01_08010000_05_0010","text":"いつものスタジオで降りる\n後は連絡とかいらねぇから"},
{"key":"SCENARIO_s01_08010000_05_0020","text":"ルカ……\nその前に、ちょっと付き合ってくれないか？"},
{"key":"SCENARIO_s01_08010000_05_0001","text":"Motion"},
{"key":"SCENARIO_s01_08010000_05_0002","text":"Motion"},
{"key":"SCENARIO_s01_08010000_05_0030","text":"たまには\nこうして息抜きしないとな"},
{"key":"SCENARIO_s01_08010000_05_0040","text":"チッ……\nなんなんだよ……"},
{"key":"SCENARIO_s01_08010000_05_0050","text":"知ってるか？\nもうすぐ彗星が近づくらしい"},
{"key":"SCENARIO_s01_08010000_05_0060","text":"ひときわ大きく、強く輝いて────"},
{"key":"SCENARIO_s01_08010000_05_0070","text":"それがどうしたんだよ"},
{"key":"SCENARIO_s01_08010000_05_0080","text":"バカみてぇ"},
{"key":"SCENARIO_s01_08010000_05_0090","text":"…………きっとすごく綺麗だと思うんだ"},
{"key":"SCENARIO_s01_08010000_05_0100","text":"でもどうせ……！"},
{"key":"SCENARIO_s01_08010000_05_0110","text":"どうせ\n消えんだよ────"},
{"key":"SCENARIO_s01_08010000_05_0120","text":"なくなるんだよ\nそんなもんは"},
{"key":"SCENARIO_s01_08010000_05_0130","text":"まぁ、そうかもしれない\nでも…………"},
{"key":"SCENARIO_s01_08010000_05_0140","text":"俺は────\nそれでもやっぱり、綺麗だって思う"},
{"key":"SCENARIO_s01_08010000_05_0003","text":"Motion"},
{"key":"SCENARIO_s01_08010000_05_0004","text":"Motion"},
{"key":"SCENARIO_s01_08010000_05_0150","text":"そりゃ彗星もそのうち離れていって\n俺たちの前から消えるのかもしれない"},
{"key":"SCENARIO_s01_08010000_05_0160","text":"どんなものにも、いつかは終わりが来るからさ……"},
{"key":"SCENARIO_s01_08010000_05_0005","text":"Motion"},
{"key":"SCENARIO_s01_08010000_05_0170","text":"でも、そうだとしても……\nその輝きは、きっと尊いものなんだと思う"},
{"key":"SCENARIO_s01_08010000_05_0180","text":"消えるために────\n輝くわけじゃない"},
{"key":"SCENARIO_s01_08010000_05_0006","text":"Motion"},
{"key":"SCENARIO_s01_08010000_05_0190","text":"だから……"},
{"key":"SCENARIO_s01_08010000_05_0200","text":"ルカにも────"}]