[{"key":"SCENARIO_s10_11800200_01_0000","text":"Motion"},
{"key":"SCENARIO_s10_11800200_01_0010","text":"It looks good on you, that costume."},
{"key":"SCENARIO_s10_11800200_01_0020","text":"It really does...\nWell, if Fuyu wears it, there isn\u0027t a costume that doesn\u0027t look good."},
{"key":"SCENARIO_s10_11800200_01_0030","text":"──Hey,\nWhen you said that, do you mean, more than anyone else?"},
{"key":"SCENARIO_s10_11800200_01_0040","text":"Eh?"},
{"key":"SCENARIO_s10_11800200_01_0050","text":"Everyone in this production has a matching costume right?\nSo I\u0027m asking, does it suit Fuyu more than anyone else."},
{"key":"SCENARIO_s10_11800200_01_0060","text":"!\nThat\u0027s..."},
{"key":"SCENARIO_s10_11800200_01_0070","text":"Aーnd Stop♡"},
{"key":"SCENARIO_s10_11800200_01_0080","text":"You\u0027re Fuyu\u0027s producer, but also everyone\u0027s producer, right?\nYou\u0027d better think this through carefully, right?"},
{"key":"SCENARIO_s10_11800200_01_0090","text":"......!"},
{"key":"SCENARIO_s10_11800200_01_0100","text":"I wonder what the correct response could be.\n...Fufu,  alright now, would youplease give me your answer?"}]
