[{"key":"SCENARIO_s01_07010000_03_0000","text":"Motion"},
{"key":"SCENARIO_s01_07010000_03_0021","text":"Motion"},
{"key":"SCENARIO_s01_07010000_03_0071","text":"Motion"},
{"key":"SCENARIO_s01_07010000_03_0081","text":"Motion"},
{"key":"SCENARIO_s01_07010000_03_0121","text":"Motion"},
{"key":"SCENARIO_s01_07010000_03_0131","text":"Motion"},
{"key":"SCENARIO_s01_07010000_03_0151","text":"Motion"},
{"key":"SCENARIO_s01_07010000_03_0171","text":"Motion"},
{"key":"SCENARIO_s01_07010000_03_0201","text":"Motion"},
{"key":"SCENARIO_s01_07010000_03_0010","text":"──Lifter?"},
{"key":"SCENARIO_s01_07010000_03_0020","text":"That\u0027s the stage director\u0027s instruction.\nI think there will be explanations during rehearsal."},
{"key":"SCENARIO_s01_07010000_03_0030","text":"Is that...\nreally necessary for the performance?"},
{"key":"SCENARIO_s01_07010000_03_0040","text":"...? Is something wrong?\nMaybe it\u0027s too high..."},
{"key":"SCENARIO_s01_07010000_03_0050","text":"No, it\u0027s okay.\nIt\u0027s just that..."},
{"key":"SCENARIO_s01_07010000_03_0060","text":"A lifter is just an up-and-down movement, right?\nIt feels like a waste of time just standing there."},
{"key":"SCENARIO_s01_07010000_03_0070","text":"Especially when there are dancers involved..."},
{"key":"SCENARIO_s01_07010000_03_0080","text":"..."},
{"key":"SCENARIO_s01_07010000_03_0090","text":"When lifted,\nit\u0027s hard to maintain eye contact with the audience..."},
{"key":"SCENARIO_s01_07010000_03_0100","text":"I see... I think it\u0027s a direction to ensure that the people\non stage can face the audience at the same eye level."},
{"key":"SCENARIO_s01_07010000_03_0110","text":"...Yeah."},
{"key":"SCENARIO_s01_07010000_03_0120","text":"...Understood. If that\u0027s the decision,\nthen I\u0027ll do my best within that framework."},
{"key":"SCENARIO_s01_07010000_03_0130","text":"What about you, Nichika?"},
{"key":"SCENARIO_s01_07010000_03_0140","text":"...Huh?"},
{"key":"SCENARIO_s01_07010000_03_0150","text":"Even though it\u0027s a lifter..."},
{"key":"SCENARIO_s01_07010000_03_0160","text":"Ah...\nUm... Of course, I\u0027ll do it!"},
{"key":"SCENARIO_s01_07010000_03_0170","text":"Okay, I\u0027ll let the stage director know.\nLet\u0027s polish up what we\u0027re good at as much as possible."},
{"key":"SCENARIO_s01_07010000_03_0180","text":"Yeah...\nI want to do everything I can."},
{"key":"SCENARIO_s01_07010000_03_0190","text":"Yes...!"},
{"key":"SCENARIO_s01_07010000_03_0200","text":"...Alright, sorry for the sudden change,\nbut I\u0027m counting on both of you."}]
