[{"key":"SCENARIO_s42_01080100_06_0000","text":"Motion"},
{"key":"SCENARIO_s42_01080100_06_0010","text":"……あ、プロデューサー──！"},
{"key":"SCENARIO_s42_01080100_06_0020","text":"おう、羽那じゃないか\n……はるきは？"},
{"key":"SCENARIO_s42_01080100_06_0030","text":"はるきちゃんは帰りの支度中\nあたしは飲み物買おうかなーって"},
{"key":"SCENARIO_s42_01080100_06_0040","text":"そうか\n飲み物、俺が買うよ。何がいい？"},
{"key":"SCENARIO_s42_01080100_06_0050","text":"あはっ、やったー\nそのお茶がいいなー"},
{"key":"SCENARIO_s42_01080100_06_0060","text":"はい、お茶"},
{"key":"SCENARIO_s42_01080100_06_0001","text":"Motion"},
{"key":"SCENARIO_s42_01080100_06_0070","text":"ありがとうっ"},
{"key":"SCENARIO_s42_01080100_06_0002","text":"Motion"},
{"key":"SCENARIO_s42_01080100_06_0003","text":"Motion"},
{"key":"SCENARIO_s42_01080100_06_0080","text":"…………\nねえ、プロデューサー"},
{"key":"SCENARIO_s42_01080100_06_0090","text":"ルカちゃんって……\nあたしとはるきちゃんのこと、どう思ってるんだろう"},
{"key":"SCENARIO_s42_01080100_06_0004","text":"Motion"},
{"key":"SCENARIO_s42_01080100_06_0100","text":"──えっ"},
{"key":"SCENARIO_s42_01080100_06_0110","text":"コメティックで一緒に活動するようになって\n少し経ったけど──"},
{"key":"SCENARIO_s42_01080100_06_0120","text":"まだあんまり仲良くなれないんだーっ"},
{"key":"SCENARIO_s42_01080100_06_0130","text":"…………"},
{"key":"SCENARIO_s42_01080100_06_0140","text":"今日だって、先にタクシーで帰っちゃったし"},
{"key":"SCENARIO_s42_01080100_06_0150","text":"……なんか\n嫌なのかもなーって"},
{"key":"SCENARIO_s42_01080100_06_0160","text":"──……\n嫌なんてこと、ないと思うぞ"},
{"key":"SCENARIO_s42_01080100_06_0170","text":"ただ──ルカも……\n大きな環境の変化があったから……"},
{"key":"SCENARIO_s42_01080100_06_0180","text":"……きっと、もう少し\n時間が必要なんだ……"},
{"key":"SCENARIO_s42_01080100_06_0190","text":"──っていうふうに\n俺には見えてるかな……"},
{"key":"SCENARIO_s42_01080100_06_0200","text":"────そっか\nルカちゃんも、大変なんだー"}]
