[{"key":"SCENARIO_s10_30900200_01_0001","text":"Motion"},
{"key":"SCENARIO_s10_30900200_01_0031","text":"Motion"},
{"key":"SCENARIO_s10_30900200_01_0081","text":"Motion"},
{"key":"SCENARIO_s10_30900200_01_0010","text":"Wow!\nA doggie!"},
{"key":"SCENARIO_s10_30900200_01_0020","text":"Oh...!\nHaha, it\u0027s so lively!"},
{"key":"SCENARIO_s10_30900200_01_0030","text":"Can I pet the\ndoggie...?"},
{"key":"SCENARIO_s10_30900200_01_0040","text":"Ehehe..."},
{"key":"SCENARIO_s10_30900200_01_0050","text":"He\u0027s so friendly!\nCute..."},
{"key":"SCENARIO_s10_30900200_01_0060","text":"Oh, he licked me."},
{"key":"SCENARIO_s10_30900200_01_0070","text":"...Did my hand smell like jerky?"},
{"key":"SCENARIO_s10_30900200_01_0080","text":"Haha!"},
{"key":"SCENARIO_s10_30900200_01_0090","text":"Kaho really loves dogs, doesn\u0027t she?"},
{"key":"SCENARIO_s10_30900200_01_0100","text":"Yes!\nI love them!"}]
