[{"key":"SCENARIO_s10_21600300_02_0000","text":"Motion"},
{"key":"SCENARIO_s10_21600300_02_0010","text":"……はい、プロデューサーさん"},
{"key":"SCENARIO_s10_21600300_02_0020","text":"ふふっ、大丈夫です\nもうあとスキンケアして眠るだけなので……"},
{"key":"SCENARIO_s10_21600300_02_0030","text":"『そうか、よかった』"},
{"key":"SCENARIO_s10_21600300_02_0040","text":"『甘奈が千雪の作った衣装モチーフのアクセサリー、\n　アップしてただろう？』"},
{"key":"SCENARIO_s10_21600300_02_0050","text":"『ファンの間で話題になってるみたいだから、\n　チェックしてみるのもいいかもって思ってさ』"},
{"key":"SCENARIO_s10_21600300_02_0060","text":"わあ、そうなんですね……？\nお知らせありがとうございます、プロデューサーさん"},
{"key":"SCENARIO_s10_21600300_02_0070","text":"ふふっ、今夜はベッドでごろごろしながら\n幸せな時間を過ごせそう……！"},
{"key":"SCENARIO_s10_21600300_02_0080","text":"『ああ、是非\n　……ファンの人たちにとってもさ』"},
{"key":"SCENARIO_s10_21600300_02_0090","text":"『千雪たちが衣装を気に入ってるっていうのがわかるの\n　嬉しいことなんだな』"},
{"key":"SCENARIO_s10_21600300_02_0100","text":"ふふっ、そうですね\n嬉しいこと、いっぱい……リレーしてます"}]