[{"key":"SCENARIO_s10_31100100_01_0000","text":"Motion"},
{"key":"SCENARIO_s10_31100100_01_0010","text":"......?\nThis ball─"},
{"key":"SCENARIO_s10_31100100_01_0019","text":"Boy"},
{"key":"SCENARIO_s10_31100100_01_0020","text":"Excuse meee! That\u0027s mine!\nCould you throw the ball over here, pleeease?!"},
{"key":"SCENARIO_s10_31100100_01_0030","text":"Okay!\nHere it comes!"},
{"key":"SCENARIO_s10_31100100_01_0040","text":"Haha, nice catch!"},
{"key":"SCENARIO_s10_31100100_01_0045","text":"Motion"},
{"key":"SCENARIO_s10_31100100_01_0050","text":"─And, be careful around here,\nthere\u0027s a lot of traffic!"},
{"key":"SCENARIO_s10_31100100_01_0059","text":"Boy"},
{"key":"SCENARIO_s10_31100100_01_0060","text":"......!\nYes, thank you very much!"},
{"key":"SCENARIO_s10_31100100_01_0070","text":"…………"},
{"key":"SCENARIO_s10_31100100_01_0080","text":"......?\nWhat\u0027s up..."},
{"key":"SCENARIO_s10_31100100_01_0090","text":"─Oh, haha...!"},
{"key":"SCENARIO_s10_31100100_01_0100","text":"That was a nice pass, Juri."}]
