[{"key":"SCENARIO_s02_01110000_01_0000","text":"Motion"},
{"key":"SCENARIO_s02_01110000_01_0010","text":"Alright,\nThat should be all for the emergency exits."},
{"key":"SCENARIO_s02_01110000_01_0020","text":"Yeah, we should have\nchecked from end to end."},
{"key":"SCENARIO_s02_01110000_01_0030","text":"But Juri, you could\u0027ve let me handle this stuff\nand enjoyed yourself until the lessons."},
{"key":"SCENARIO_s02_01110000_01_0040","text":"Isn\u0027t that part of the camp too?\nWe shouldn\u0027t rely on the producer for everything."},
{"key":"SCENARIO_s02_01110000_01_0050","text":"Haha, that\u0027s true."},
{"key":"SCENARIO_s02_01110000_01_0060","text":"It\u0027s not that we\u0027re not counting on you\nit\u0027s just..."},
{"key":"SCENARIO_s02_01110000_01_0070","text":"The producer has a lot to do, right?\nWe can handle safety checks and stuff too."},
{"key":"SCENARIO_s02_01110000_01_0080","text":"Yeah, I thought\nyou meant it that way from the start."},
{"key":"SCENARIO_s02_01110000_01_0090","text":"Come on, you should\u0027ve said that earlier."},
{"key":"SCENARIO_s02_01110000_01_0100","text":"Haha, sorry about that."},
{"key":"SCENARIO_s02_01110000_01_0110","text":"But really, I want to help you guys out.\nI want you to enjoy the camp the most."},
{"key":"SCENARIO_s02_01110000_01_0120","text":"Yeah... I see."},
{"key":"SCENARIO_s02_01110000_01_0130","text":"In that case, you don\u0027t have to worry.\nIt\u0027s bound to be fun, always."}]
