[{"key":"SCENARIO_s03_05010000_00_0011","text":"Motion"},
{"key":"SCENARIO_s03_05010000_00_0010","text":"あははっ\nプロデューサーさん、おっきなあくびっす"},
{"key":"SCENARIO_s03_05010000_00_0020","text":"す、すまん\n寝てはいるんだが頭が冴えなくてな"},
{"key":"SCENARIO_s03_05010000_00_0030","text":"マジで～？\nこれから仕事っしょ？"},
{"key":"SCENARIO_s03_05010000_00_0040","text":"ちゃんと目を覚ましておきなさいよ"},
{"key":"SCENARIO_s03_05010000_00_0004","text":"コーヒーにしよう"},
{"key":"SCENARIO_s03_05010000_00_0005","text":"軽く\nストレッチとか"},
{"key":"SCENARIO_s03_05010000_00_0006","text":"何かお腹に\n入れるか……"},
{"key":"SCENARIO_s03_05010000_01_0011","text":"Motion"},
{"key":"SCENARIO_s03_05010000_01_0010","text":"……あとちょっとでお湯が沸くわ\nそしたら一緒にいれてあげる"},
{"key":"SCENARIO_s03_05010000_01_0020","text":"あっ……ありがとう冬優子\n助かるよ"},
{"key":"SCENARIO_s03_05010000_02_0011","text":"Motion"},
{"key":"SCENARIO_s03_05010000_02_0010","text":"いっすね～！\nわたしも一緒にやるっすよ"},
{"key":"SCENARIO_s03_05010000_02_0020","text":"はは……あさひについていけるかなあ"},
{"key":"SCENARIO_s03_05010000_03_0011","text":"Motion"},
{"key":"SCENARIO_s03_05010000_03_0010","text":"あ、じゃーパン持ってるからあげる～"},
{"key":"SCENARIO_s03_05010000_03_0020","text":"えっ、いいのか？\nありがとな、愛依"}]
