[{"key":"SCENARIO_s20_12700100_02_0000","text":"Motion"},
{"key":"SCENARIO_s20_12700100_02_0041","text":"Motion"},
{"key":"SCENARIO_s20_12700100_02_0010","text":"My friend from Okayama keeps sending me\nmessages like, \u0022Bought the magazine!\u0022"},
{"key":"SCENARIO_s20_12700100_02_0020","text":"It\u0027s kind of strange\nhow our work reaches that far, isn\u0027t it?"},
{"key":"SCENARIO_s20_12700100_02_0030","text":"Oh, right.\nLet\u0027s promote Haruki to our friends!"},
{"key":"SCENARIO_s20_12700100_02_0040","text":"Hehe... Thanks~. But I think your friends\nwould want to hear about Hana-chan too..."},
{"key":"SCENARIO_s20_12700100_02_0050","text":"Haha, they\u0027re both getting excited, huh?"},
{"key":"SCENARIO_s20_12700100_02_0060","text":"Hehe, yeah. I never thought\nwe\u0027d be featured in magazines so quickly."},
{"key":"SCENARIO_s20_12700100_02_0070","text":"That\u0027s true... It means people have\nhigh expectations for both of you."},
{"key":"SCENARIO_s20_12700100_02_0080","text":"It must be a dream come true for people\nin your hometown to see your faces every day."},
{"key":"SCENARIO_s20_12700100_02_0090","text":"......!"},
{"key":"SCENARIO_s20_12700100_02_0100","text":"Right... So, we have to work hard\nto make that dream come true."}]
