[{"key":"SCENARIO_s02_01100000_01_0010","text":"（──あれ……？）"},
{"key":"SCENARIO_s02_01100000_01_0000","text":"Motion"},
{"key":"SCENARIO_s02_01100000_01_0020","text":"……お鍋は──……？　こっちか\n包丁とまな板……"},
{"key":"SCENARIO_s02_01100000_01_0030","text":"──ここね、おっけー"},
{"key":"SCENARIO_s02_01100000_01_0040","text":"！"},
{"key":"SCENARIO_s02_01100000_01_0001","text":"Motion"},
{"key":"SCENARIO_s02_01100000_01_0050","text":"どうかしたか？　智代子\n何か探し物とか──"},
{"key":"SCENARIO_s02_01100000_01_0060","text":"あっ、いえ！　違うんです！\nすみません……！"},
{"key":"SCENARIO_s02_01100000_01_0070","text":"器具とか、何がどこにしまわれてるのかな～って\nちょっと確認してみてただけで……！"},
{"key":"SCENARIO_s02_01100000_01_0080","text":"ああ、そういうことか"},
{"key":"SCENARIO_s02_01100000_01_0090","text":"──しっかりしてるなぁ"},
{"key":"SCENARIO_s02_01100000_01_0100","text":"全然！　全然！\nたまたまですから……！"},
{"key":"SCENARIO_s02_01100000_01_0110","text":"美味しくご飯ができるかどうかは合宿の死活問題ですし！\nかっこつかないと困っちゃいますのでね！"},
{"key":"SCENARIO_s02_01100000_01_0120","text":"はは、なるほど！"},
{"key":"SCENARIO_s02_01100000_01_0130","text":"──……何か手伝えることはあるか？"},
{"key":"SCENARIO_s02_01100000_01_0140","text":"！\n……──えっと、じゃあ"},
{"key":"SCENARIO_s02_01100000_01_0150","text":"菜箸が見つからないんです\n一緒に探してもらえますか？"},
{"key":"SCENARIO_s02_01100000_01_0160","text":"おう、了解だ"},
{"key":"SCENARIO_s02_01100000_01_0002","text":"Motion"}]