[{"key":"SCENARIO_s10_10300200_03_0000","text":"Motion"},
{"key":"SCENARIO_s10_10300200_03_0010","text":"Tomorrow\u0027s schedule is set. We\u0027ll enter the venue at\n10 a.m, and the recording is scheduled to start at 2 p.m."},
{"key":"SCENARIO_s10_10300200_03_0020","text":"The building itself is quite large, so there\u0027s quite a\nbit of moving around inside, as the staff mentioned."},
{"key":"SCENARIO_s10_10300200_03_0030","text":"…………"},
{"key":"SCENARIO_s10_10300200_03_0040","text":"So here\u0027s the thing."},
{"key":"SCENARIO_s10_10300200_03_0050","text":"...Right."},
{"key":"SCENARIO_s10_10300200_03_0060","text":"I want to make sure once again that I don\u0027t\nmake the same mistakes I did before."},
{"key":"SCENARIO_s10_10300200_03_0070","text":"Roger that...!"},
{"key":"SCENARIO_s10_10300200_03_0080","text":"We enter at 10 a.m., and recording starts at 2 p.m.!"},
{"key":"SCENARIO_s10_10300200_03_0090","text":"Thanks, I\u0027ll double-check too."},
{"key":"SCENARIO_s10_10300200_03_0100","text":"Alright!\nLet\u0027s give it our all tomorrow too, Producer!"}]
