[{"key":"SCENARIO_s20_21200100_03_0001","text":"Motion"},
{"key":"SCENARIO_s20_21200100_03_0010","text":"おはようございます！"},
{"key":"SCENARIO_s20_21200100_03_0020","text":"『果穂さん』"},
{"key":"SCENARIO_s20_21200100_03_0030","text":"お疲れ様でーす！"},
{"key":"SCENARIO_s20_21200100_03_0040","text":"『智代子さん』"},
{"key":"SCENARIO_s20_21200100_03_0050","text":"お疲れー！"},
{"key":"SCENARIO_s20_21200100_03_0060","text":"『樹里さん』"},
{"key":"SCENARIO_s20_21200100_03_0002","text":"Motion"},
{"key":"SCENARIO_s20_21200100_03_0003","text":"Motion"},
{"key":"SCENARIO_s20_21200100_03_0070","text":"あら、みんな早いわね"},
{"key":"SCENARIO_s20_21200100_03_0080","text":"『夏葉さん』"},
{"key":"SCENARIO_s20_21200100_03_0004","text":"Motion"},
{"key":"SCENARIO_s20_21200100_03_0005","text":"Motion"},
{"key":"SCENARIO_s20_21200100_03_0090","text":"『みなさまが来られ、\n　凛世の一日が始まります』"},
{"key":"SCENARIO_s20_21200100_03_0100","text":"『父さま、母さま、みなさまの一日も\n　あたたかく楽しいものでありますよう。草々』"}]
