[{"key":"SCENARIO_s02_02250000_03_0000","text":"Motion"},
{"key":"SCENARIO_s02_02250000_03_0010","text":"Good job."},
{"key":"SCENARIO_s02_02250000_03_0020","text":"Oh, Mikoto.\nGood job."},
{"key":"SCENARIO_s02_02250000_03_0030","text":"You\u0027re punctual.\nWould you like something to drink?"},
{"key":"SCENARIO_s02_02250000_03_0040","text":"No, I\u0027m fine.\nThank you for letting me use the rehearsal room until late."},
{"key":"SCENARIO_s02_02250000_03_0050","text":"Alright, I\u0027ll return the key then."},
{"key":"SCENARIO_s02_02250000_03_0060","text":"Well, from our perspective...\nwe also want you to rest properly."},
{"key":"SCENARIO_s02_02250000_03_0070","text":"Especially now that the performance is coming up,\nwe want you to take care of yourself, or rather..."},
{"key":"SCENARIO_s02_02250000_03_0080","text":"......Thank you.\nBut, I don\u0027t want to have any regrets."},
{"key":"SCENARIO_s02_02250000_03_0090","text":"I want to do everything I can."},
{"key":"SCENARIO_s02_02250000_03_0100","text":"I see..."},
{"key":"SCENARIO_s02_02250000_03_0110","text":"But...\nAre you feeling any burden?"},
{"key":"SCENARIO_s02_02250000_03_0120","text":"Huh?"},
{"key":"SCENARIO_s02_02250000_03_0130","text":"You know...\nThe performance has changed a bit, hasn\u0027t it?"},
{"key":"SCENARIO_s02_02250000_03_0140","text":"Are you saying that dancing contemporary alone\nmight be a burden?"},
{"key":"SCENARIO_s02_02250000_03_0150","text":"If that\u0027s the case, don\u0027t worry. I\u0027ll always\ndeliver the best performance as usual."},
{"key":"SCENARIO_s02_02250000_03_0160","text":"I see..."},
{"key":"SCENARIO_s02_02250000_03_0170","text":"I\u0027m looking forward to it.\nSHHis\u0027s... performance."},
{"key":"SCENARIO_s02_02250000_03_0180","text":"Yeah.\nExpect it, Producer."}]
