[{"key":"SCENARIO_s02_02140000_01_0000","text":"Motion"},
{"key":"SCENARIO_s02_02140000_01_0010","text":"──コーヒー、お待たせしました☆\nブラックでいいんだよねー？"},
{"key":"SCENARIO_s02_02140000_01_0020","text":"ああ、ありがとう\n悪いな……資料を届けに来ただけなのに"},
{"key":"SCENARIO_s02_02140000_01_0030","text":"ううん、わざわざ来てくれたんだもん\n玄関で済ますなんてできないよー"},
{"key":"SCENARIO_s02_02140000_01_0040","text":"あっ、でも忙しいなら、\n本当に無理しなくていいからね……？"},
{"key":"SCENARIO_s02_02140000_01_0050","text":"はは、今日は大丈夫だ\nじゃあ……ありがたくいただくよ"},
{"key":"SCENARIO_s02_02140000_01_0060","text":"どうぞ！　召し上がれー\n美味しく淹れられてるかな？"},
{"key":"SCENARIO_s02_02140000_01_0070","text":"…………\nああ、美味しい"},
{"key":"SCENARIO_s02_02140000_01_0080","text":"よかった☆\nえへへっ……"},
{"key":"SCENARIO_s02_02140000_01_0090","text":"……なんかプロデューサーさんが、\nうちにいるのって不思議な感じだね～"},
{"key":"SCENARIO_s02_02140000_01_0091","text":"Motion"},
{"key":"SCENARIO_s02_02140000_01_0100","text":"──あっ、そうだ！\nプロデューサーさんに見せたい写真があったの！"},
{"key":"SCENARIO_s02_02140000_01_0110","text":"小さい頃の甜花ちゃんと甘奈が、\nお遊戯会でね、一緒に歌って踊った時の……ほらこれ！"},
{"key":"SCENARIO_s02_02140000_01_0120","text":"お、ふたりとも可愛い服を着て……\nはは、この時からアイドルみたいだな"},
{"key":"SCENARIO_s02_02140000_01_0130","text":"えへへ、そうでしょー\nだから、見せたいなって思ってたんだ"},
{"key":"SCENARIO_s02_02140000_01_0140","text":"──この小さかった甘奈を、\n本物のアイドルにしてくれたのはプロデューサーさん"},
{"key":"SCENARIO_s02_02140000_01_0150","text":"甘奈ね、アイドルになってよかったって……\n心の底から思ってる。──だから本当にありがとう"},
{"key":"SCENARIO_s02_02140000_01_0160","text":"えへへっ……この時に比べたら、\n今の甘奈、ちょっとは成長できたかな……？"},
{"key":"SCENARIO_s02_02140000_01_0170","text":"あっ、でも変わってないとこもあるかも\n癖とか、苦手な食べ物とか……あと──"},
{"key":"SCENARIO_s02_02140000_01_0180","text":"甘奈の大好きとか……この時からずーっと……\nなーんにも変わってないんだなーって……"}]