[{"key":"SCENARIO_s09_01011600_01_0000","text":"Motion"},
{"key":"SCENARIO_s09_01011600_01_0010","text":"Good morning, Producer-san."},
{"key":"SCENARIO_s09_01011600_01_0020","text":"Ah, good morning, Chiyuki..."},
{"key":"SCENARIO_s09_01011600_01_0030","text":"......?\nIs something wrong?"},
{"key":"SCENARIO_s09_01011600_01_0040","text":"Chiyuki...\nThere\u0027s something stuck in your hair..."},
{"key":"SCENARIO_s09_01011600_01_0050","text":"Huh?"},
{"key":"SCENARIO_s09_01011600_01_0060","text":"Oh, it\u0027s a thread!"},
{"key":"SCENARIO_s09_01011600_01_0070","text":"I-I\u0027m sorry... It seems a stray piece of\nembroidery thread got stuck..."},
{"key":"SCENARIO_s09_01011600_01_0080","text":"No, no, don\u0027t worry about it.\nEmbroidery in the morning?"},
{"key":"SCENARIO_s09_01011600_01_0090","text":"Yes... I just wanted to make some progress,\neven if it\u0027s just a little."},
{"key":"SCENARIO_s09_01011600_01_0100","text":"Haha, you\u0027re really motivated, huh? You even went\nout of your way to ask if you could bring it in beforehand."},
{"key":"SCENARIO_s09_01011600_01_0110","text":"No, I really...\nneed to focus more on the training camp..."},
{"key":"SCENARIO_s09_01011600_01_0120","text":"Haha, it\u0027s just a bit of thread, no need to make a fuss.\nI said you could bring it, didn\u0027t I?"},
{"key":"SCENARIO_s09_01011600_01_0130","text":"............"},
{"key":"SCENARIO_s09_01011600_01_0140","text":"And I won\u0027t meddle with\nwhat\u0027s important to you, Chiyuki."},
{"key":"SCENARIO_s09_01011600_01_0150","text":"As long as you don\u0027t push yourself too hard."},
{"key":"SCENARIO_s09_01011600_01_0160","text":"...Thank you very much.\nI\u0027ll make sure to keep that in mind."},
{"key":"SCENARIO_s09_01011600_01_0170","text":"Yeah, we have lessons now.\nLet\u0027s focus."},
{"key":"SCENARIO_s09_01011600_01_0180","text":"──Yes."}]
