[{"key":"SCENARIO_s03_04090000_00_0001","text":"Motion"},
{"key":"SCENARIO_s03_04090000_00_0010","text":"甘奈ちゃん、甜花ちゃん\r\nさっき、出先でドーナツいただいたの"},
{"key":"SCENARIO_s03_04090000_00_0020","text":"一緒に食べない？\r\nよければ、プロデューサーさんも……"},
{"key":"SCENARIO_s03_04090000_00_0030","text":"じゃあ甘奈は\n飲み物用意するねっ！"},
{"key":"SCENARIO_s03_04090000_00_0040","text":"あ……\nバターの、いい匂い……！"},
{"key":"SCENARIO_s03_04090000_00_0005","text":"ドーナツ、\nいいよな"},
{"key":"SCENARIO_s03_04090000_00_0006","text":"俺は皿を\n出しておこう"},
{"key":"SCENARIO_s03_04090000_00_0007","text":"お礼メール、\nしておくよ"},
{"key":"SCENARIO_s03_04090000_01_0001","text":"Motion"},
{"key":"SCENARIO_s03_04090000_01_0010","text":"箱の中に、いろんな種類が入ってるとさ……\n選ぶのも楽しくて、いいよな"},
{"key":"SCENARIO_s03_04090000_01_0020","text":"ふふっ、このわくわく……\r\nプロデューサーさんもわかってくださいます？"},
{"key":"SCENARIO_s03_04090000_02_0001","text":"Motion"},
{"key":"SCENARIO_s03_04090000_02_0010","text":"ありがと、プロデューサーさん！"},
{"key":"SCENARIO_s03_04090000_02_0020","text":"飲み物も、もうすぐできるからねー！\n座って待っててくれていいよ！"},
{"key":"SCENARIO_s03_04090000_03_0001","text":"Motion"},
{"key":"SCENARIO_s03_04090000_03_0010","text":"ありがとうございます……！\r\n後でお名刺、お渡ししますね"},
{"key":"SCENARIO_s03_04090000_03_0020","text":"でも今は……\r\nゆっくりドーナツタイム、しましょう？"}]